prefixfuzz-0.1.1.dist-info/METADATA
prefixfuzz-0.1.1.dist-info/WHEEL
prefixfuzz/__init__.py
prefixfuzz/_prefixfuzz.pypy311-pp73-s390x-linux-gnu.so
prefixfuzz/prefix_search_builder.py
prefixfuzz-0.1.1.dist-info/RECORD
