Metadata-Version: 2.4
Name: prefixfuzz
Version: 0.1.1
Classifier: Programming Language :: Rust
Classifier: Programming Language :: Python
Summary: Fuzzy prefix search implementation for Rust and Python.
Requires-Python: >=3.10
